alien_language/__init__.py
alien_language/translator.py
alien_language-0.2.2.dist-info/METADATA
alien_language-0.2.2.dist-info/WHEEL
alien_language-0.2.2.dist-info/entry_points.txt
alien_language-0.2.2.dist-info/top_level.txt
alien_language-0.2.2.dist-info/RECORD
