Metadata-Version: 2.2
Name: alien_language
Version: 0.2.2
Summary: A Python to Alien Language translator. Translate Python code into a fun, alien-like syntax!
Home-page: https://github.com/ishanoshada/alien-language
Author: Ishan Oshada
Author-email: ishan.kodithuwakku.offical@gmail.com
License: MIT
Project-URL: Source Code, https://github.com/ishanoshada/alien-language
Project-URL: Bug Tracker, https://github.com/ishanoshada/alien-language/issues
Project-URL: Documentation, https://github.com/ishanoshada/alien-language#readme
Keywords: alien language,python translator,fun programming,code translation,python to alien,programming language
Classifier: Development Status :: 4 - Beta
Classifier: Intended Audience :: Developers
Classifier: Intended Audience :: Education
Classifier: License :: OSI Approved :: MIT License
Classifier: Programming Language :: Python :: 3
Classifier: Programming Language :: Python :: 3.7
Classifier: Programming Language :: Python :: 3.8
Classifier: Programming Language :: Python :: 3.9
Classifier: Programming Language :: Python :: 3.10
Classifier: Programming Language :: Python :: 3.11
Classifier: Operating System :: OS Independent
Classifier: Topic :: Software Development :: Libraries :: Python Modules
Classifier: Topic :: Software Development :: Interpreters
Classifier: Topic :: Education
Classifier: Topic :: Games/Entertainment
Dynamic: author
Dynamic: author-email
Dynamic: classifier
Dynamic: description
Dynamic: description-content-type
Dynamic: home-page
Dynamic: keywords
Dynamic: license
Dynamic: project-url
Dynamic: summary
